Augment70171/__init__.py
Augment70171/detector_data_augmentation.py
augment70171-2.0.dist-info/METADATA
augment70171-2.0.dist-info/WHEEL
augment70171-2.0.dist-info/licenses/LICENSE
augment70171-2.0.dist-info/RECORD
